flask_midtrans/__init__.py
tests/__init__.py
tests/test_midtrans.py
flask_midtrans-0.0.1a0.dist-info/LICENCE
flask_midtrans-0.0.1a0.dist-info/METADATA
flask_midtrans-0.0.1a0.dist-info/WHEEL
flask_midtrans-0.0.1a0.dist-info/top_level.txt
flask_midtrans-0.0.1a0.dist-info/RECORD
